pybrainuz/__init__.py
pybrainuz/app.py
pybrainuz/middleware.py
pybrainuz/response.py
pybraineuz-0.1.2.dist-info/METADATA
pybraineuz-0.1.2.dist-info/WHEEL
pybraineuz-0.1.2.dist-info/top_level.txt
pybraineuz-0.1.2.dist-info/RECORD
